ens_sdk/__init__.py
ens_sdk/ens.py
ens_sdk/utils/__init__.py
ens_sdk/utils/cache.py
ens_sdk/utils/timezone.py
ens_sdk-0.0.13.dist-info/METADATA
ens_sdk-0.0.13.dist-info/WHEEL
ens_sdk-0.0.13.dist-info/licenses/LICENSE
ens_sdk-0.0.13.dist-info/RECORD
